electric_units
