Metadata-Version: 2.1
Name: electric-units
Version: 1.0.1
Summary: For handling units of measurement in electricity grid data.
Home-page: http://github.com/ample-tech/electric-units
Author: ample sustainable brands
Author-email: administrator@ample.tech
License: MIT
Keywords: energy,grid,data,data transformation
Platform: UNKNOWN
Classifier: Development Status :: 5 - Production/Stable
Classifier: Intended Audience :: Developers
Classifier: Topic :: Scientific/Engineering :: Information Analysis
Classifier: License :: OSI Approved :: MIT License
Classifier: Programming Language :: Python :: 3
Provides-Extra: pandas
